<trafficdata><sim_execution duration="0" id="528ee21d8010937a84e3f1c6" running="false" stepsize="2" /><vehicles><vehicle id="flow_19457616#2.0" lat="36.142944417" lng="-86.8101990254" type="Truck" /><vehicle id="flow_19457616#7.0" lat="36.1368583177" lng="-86.8111661461" type="Car" /><vehicle id="flow_19457616#7.1" lat="36.1370689251" lng="-86.8111427669" type="Truck" /><vehicle id="flow_19479457#1.0" lat="36.142331642" lng="-86.8048645791" type="Bus" /><vehicle id="flow_19479457#1.1" lat="36.1424753503" lng="-86.804845524" type="Car" /><vehicle id="flow_19479459#3.0" lat="36.1315420277" lng="-86.8059628488" type="Bus" /><vehicle id="flow_19479459#3.1" lat="36.1316866808" lng="-86.8059416328" type="Car" /><vehicle id="flow_19479801#3.0" lat="36.1373233557" lng="-86.7972068221" type="Car" /><vehicle id="flow_19479801#3.1" lat="36.1373042313" lng="-86.7970322886" type="Car" /><vehicle id="flow_19485812#0.0" lat="36.1424573846" lng="-86.8153992824" type="Car" /><vehicle id="flow_19485812#0.1" lat="36.1425103604" lng="-86.8154387014" type="Bus" /></vehicles></trafficdata>